{"country": "FR", "year": 2022, "baseload_price": 275.89, "peakload_price": 317.09, "offpeak_price": 253.11, "price_p05": 95.9, "price_p25": 183.03, "price_median": 239.32, "price_p75": 350.0, "price_p95": 553.36, "price_stddev": 145.85, "capture_rate_pv": 291.5, "capture_rate_wind": 234.03, "capture_rate_wind_on": 234.03, "capture_rate_wind_off": NaN, "capture_ratio_pv": 1.0566, "capture_ratio_wind": 0.8483, "h_regime_a": 0, "h_regime_b": 681, "h_regime_c": 7267, "h_regime_d_tail": 808, "h_negative": 4, "h_below_5": 45, "h_above_100": 8247, "h_above_200": 5844, "spread_p95_p05": 457.46, "days_spread_above_50": 361, "avg_daily_spread": 174.43, "max_daily_spread": 2719.97, "sr": 0.004, "sr_hours": 0.0778, "far_structural": 0.9774, "far_observed": 0.5739, "ir": 0.7148, "ttl": 564.58, "vre_share": 0.1283, "pv_share": 0.042, "wind_share": 0.0863, "total_load_twh": 444.49, "total_vre_twh": 54.86, "total_surplus_twh": 1.776, "total_surplus_unabs_twh": 0.0, "data_completeness": 0.9995, "regime_coherence": 0.8684, "is_outlier": true}